{"49045": {"res": {"trans": {"total": 27764, "drove": 20501, "carpool": 4964, "transit": 348, "bike": 62, "walk": 450, "other": 129, "wfh": 1269}, "time": {"total": 26495, "lt10": 4512, "t10_19": 6187, "t20_29": 3324, "t30_44": 6554, "t45_59": 3666, "t60plus": 2252}}, "wrk": {"trans": {"total": 17630, "drove": 12576, "carpool": 3217, "transit": 93, "bike": 62, "walk": 331, "other": 82, "wfh": 1269}, "time": {"total": 16361, "lt10": 4142, "t10_19": 5754, "t20_29": 2061, "t30_44": 1539, "t45_59": 1207, "t60plus": 1658}}}, "49043": {"res": {"trans": {"total": 21359, "drove": 15612, "carpool": 1384, "transit": 349, "bike": 184, "walk": 469, "other": 338, "wfh": 2966}, "time": {"total": 18393, "lt10": 3112, "t10_19": 5201, "t20_29": 3220, "t30_44": 4211, "t45_59": 1526, "t60plus": 1123}}, "wrk": {"trans": {"total": 25429, "drove": 18560, "carpool": 2642, "transit": 401, "bike": 186, "walk": 434, "other": 193, "wfh": 2966}, "time": {"total": 22463, "lt10": 3080, "t10_19": 5464, "t20_29": 4647, "t30_44": 6040, "t45_59": 1735, "t60plus": 1497}}}, "49051": {"res": {"trans": {"total": 14118, "drove": 11099, "carpool": 1728, "transit": 5, "bike": 35, "walk": 214, "other": 50, "wfh": 945}, "time": {"total": 13173, "lt10": 3382, "t10_19": 2655, "t20_29": 1999, "t30_44": 3013, "t45_59": 1324, "t60plus": 800}}, "wrk": {"trans": {"total": 9325, "drove": 6962, "carpool": 1138, "transit": 0, "bike": 35, "walk": 200, "other": 16, "wfh": 945}, "time": {"total": 8380, "lt10": 3306, "t10_19": 2387, "t20_29": 621, "t30_44": 852, "t45_59": 726, "t60plus": 488}}}, "49003": {"res": {"trans": {"total": 22071, "drove": 17154, "carpool": 3257, "transit": 158, "bike": 48, "walk": 337, "other": 149, "wfh": 883}, "time": {"total": 21188, "lt10": 5495, "t10_19": 5398, "t20_29": 3159, "t30_44": 4330, "t45_59": 1280, "t60plus": 1526}}, "wrk": {"trans": {"total": 18549, "drove": 14114, "carpool": 2883, "transit": 85, "bike": 42, "walk": 341, "other": 157, "wfh": 883}, "time": {"total": 17666, "lt10": 5398, "t10_19": 4843, "t20_29": 2484, "t30_44": 2752, "t45_59": 1109, "t60plus": 1080}}}, "49049": {"res": {"trans": {"total": 253216, "drove": 185390, "carpool": 29757, "transit": 4993, "bike": 2714, "walk": 10349, "other": 1829, "wfh": 16856}, "time": {"total": 236360, "lt10": 43618, "t10_19": 86280, "t20_29": 46881, "t30_44": 34972, "t45_59": 12615, "t60plus": 11994}}, "wrk": {"trans": {"total": 234595, "drove": 172049, "carpool": 27495, "transit": 2761, "bike": 2667, "walk": 10269, "other": 1263, "wfh": 16856}, "time": {"total": 217739, "lt10": 43416, "t10_19": 85339, "t20_29": 44665, "t30_44": 29881, "t45_59": 8048, "t60plus": 6390}}}, "49057": {"res": {"trans": {"total": 114200, "drove": 91854, "carpool": 11856, "transit": 2087, "bike": 563, "walk": 1450, "other": 759, "wfh": 5282}, "time": {"total": 108918, "lt10": 16512, "t10_19": 40762, "t20_29": 25071, "t30_44": 13388, "t45_59": 6367, "t60plus": 6818}}, "wrk": {"trans": {"total": 106675, "drove": 87215, "carpool": 9994, "transit": 1354, "bike": 537, "walk": 1443, "other": 617, "wfh": 5282}, "time": {"total": 101393, "lt10": 16655, "t10_19": 41689, "t20_29": 24352, "t30_44": 11714, "t45_59": 3556, "t60plus": 3427}}}, "49035": {"res": {"trans": {"total": 556953, "drove": 418591, "carpool": 63787, "transit": 21047, "bike": 4716, "walk": 12421, "other": 3614, "wfh": 30997}, "time": {"total": 525956, "lt10": 55782, "t10_19": 175442, "t20_29": 149583, "t30_44": 101968, "t45_59": 25495, "t60plus": 17686}}, "wrk": {"trans": {"total": 639233, "drove": 484992, "carpool": 72601, "transit": 26748, "bike": 4810, "walk": 12483, "other": 4518, "wfh": 30997}, "time": {"total": 608236, "lt10": 57278, "t10_19": 183099, "t20_29": 164712, "t30_44": 128357, "t45_59": 42342, "t60plus": 32448}}}, "49011": {"res": {"trans": {"total": 155740, "drove": 124007, "carpool": 14799, "transit": 3895, "bike": 636, "walk": 2223, "other": 1122, "wfh": 8641}, "time": {"total": 147099, "lt10": 21194, "t10_19": 48839, "t20_29": 34208, "t30_44": 26826, "t45_59": 9638, "t60plus": 6394}}, "wrk": {"trans": {"total": 119335, "drove": 93620, "carpool": 12198, "transit": 1162, "bike": 551, "walk": 2067, "other": 684, "wfh": 8641}, "time": {"total": 110694, "lt10": 20140, "t10_19": 42349, "t20_29": 24765, "t30_44": 15563, "t45_59": 4435, "t60plus": 3442}}}, "49029": {"res": {"trans": {"total": 4644, "drove": 3950, "carpool": 384, "transit": 16, "bike": 10, "walk": 54, "other": 39, "wfh": 179}, "time": {"total": 4465, "lt10": 848, "t10_19": 798, "t20_29": 702, "t30_44": 1183, "t45_59": 475, "t60plus": 459}}, "wrk": {"trans": {"total": 1999, "drove": 1502, "carpool": 239, "transit": 0, "bike": 10, "walk": 54, "other": 15, "wfh": 179}, "time": {"total": 1820, "lt10": 796, "t10_19": 482, "t20_29": 189, "t30_44": 287, "t45_59": 33, "t60plus": 33}}}, "49005": {"res": {"trans": {"total": 56199, "drove": 41858, "carpool": 6481, "transit": 1189, "bike": 872, "walk": 2250, "other": 407, "wfh": 2907}, "time": {"total": 53292, "lt10": 15830, "t10_19": 23218, "t20_29": 6628, "t30_44": 3811, "t45_59": 1365, "t60plus": 2440}}, "wrk": {"trans": {"total": 55860, "drove": 42084, "carpool": 6076, "transit": 1206, "bike": 859, "walk": 2224, "other": 267, "wfh": 2907}, "time": {"total": 52953, "lt10": 15653, "t10_19": 23133, "t20_29": 7085, "t30_44": 4504, "t45_59": 1200, "t60plus": 1378}}}, "49023": {"res": {"trans": {"total": 4451, "drove": 3319, "carpool": 622, "transit": 9, "bike": 7, "walk": 182, "other": 5, "wfh": 306}, "time": {"total": 4145, "lt10": 1754, "t10_19": 540, "t20_29": 335, "t30_44": 739, "t45_59": 415, "t60plus": 362}}, "wrk": {"trans": {"total": 3573, "drove": 2597, "carpool": 485, "transit": 1, "bike": 5, "walk": 175, "other": 3, "wfh": 306}, "time": {"total": 3267, "lt10": 1704, "t10_19": 583, "t20_29": 205, "t30_44": 381, "t45_59": 169, "t60plus": 225}}}}